flake8_mock_spec.py
flake8_mock_spec-1.4.0.dist-info/WHEEL
flake8_mock_spec-1.4.0.dist-info/LICENSE
flake8_mock_spec-1.4.0.dist-info/METADATA
flake8_mock_spec-1.4.0.dist-info/entry_points.txt
flake8_mock_spec-1.4.0.dist-info/RECORD
